pyVBRc/__init__.py
pyVBRc/logging.py
pyVBRc/pyVBRc.py
pyVBRc/vbrc_structure.py
pyVBRc/materials/__init__.py
pyVBRc/materials/_stiffness.py
pyVBRc/materials/materials.py
pyVBRc/materials/tests/__init__.py
pyVBRc/materials/tests/test_anisotropy.py
pyVBRc/materials/tests/test_isotropic_mixtures.py
pyVBRc/sample_data/VBRc_sample_LUT.mat
pyVBRc/sample_data/VBRc_sample_LUT_R2021a.mat
pyVBRc/sample_data/VBRc_sample_LUT_v1pt0pt0.mat
pyVBRc/sample_data/__init__.py
pyVBRc/sample_data/generate_sample_vbr_struct_file.m
pyVBRc/sample_data/sample_data.py
pyVBRc/tests/__init__.py
pyVBRc/tests/test_pyVBRc.py
pyVBRc/tests/test_sample_data.py
pyVBRc-0.3.2.dist-info/LICENSE
pyVBRc-0.3.2.dist-info/METADATA
pyVBRc-0.3.2.dist-info/WHEEL
pyVBRc-0.3.2.dist-info/top_level.txt
pyVBRc-0.3.2.dist-info/RECORD
