Metadata-Version: 2.1
Name: pyVBRc
Version: 0.3.2
Summary: python utilities for working with the VBRc
Author-email: Chris Havlin <chris.havlin@gmail.com>
Project-URL: Homepage, https://github.com/vbr-calc/pyVBRc
Project-URL: Bug Tracker, https://github.com/vbr-calc/pyVBRc/issues
Classifier: Intended Audience :: Science/Research
Classifier: License :: OSI Approved :: MIT License
Classifier: Natural Language :: English
Classifier: Programming Language :: Python :: 3
Classifier: Programming Language :: Python :: 3.9
Classifier: Programming Language :: Python :: 3.10
Classifier: Programming Language :: Python :: 3.11
Requires-Python: >=3.9
License-File: LICENSE
Requires-Dist: numpy
Requires-Dist: scipy
Requires-Dist: matplotlib
Requires-Dist: packaging
Requires-Dist: unyt
Provides-Extra: dev
Requires-Dist: pytest >=3 ; extra == 'dev'
Requires-Dist: pytest-cov ; extra == 'dev'
Requires-Dist: pre-commit ; extra == 'dev'
